cflow/__init__.py
cflow/__main__.py
cflow/cancel.py
cflow/display.py
cflow/download.py
cflow/error.py
cflow/metadata.py
cflow/queue.py
cflow/runner.py
cflow/status.py
cflow/subcommand.py
cflow/submit.py
cflow-0.1.0.data/scripts/cflow
tests/__init__.py
tests/test_client.py
cflow-0.1.0.dist-info/METADATA
cflow-0.1.0.dist-info/WHEEL
cflow-0.1.0.dist-info/top_level.txt
cflow-0.1.0.dist-info/RECORD
